{
    "0": {
        "Session_code": "",
        "ID": "Zip384"
    },
    "1": {
        "Session_code": "",
        "ID": "Eig507"
    },
    "2": {
        "Session_code": "",
        "ID": "Diq063"
    },
    "3": {
        "Session_code": "",
        "ID": "Wat628"
    },
    "4": {
        "Session_code": "",
        "ID": "Cor826"
    },
    "5": {
        "Session_code": "",
        "ID": "Gem917"
    },
    "6": {
        "Session_code": "",
        "ID": "Vuw994"
    },
    "7": {
        "Session_code": "",
        "ID": "Noh213"
    },
    "8": {
        "Session_code": "",
        "ID": "Foy765"
    },
    "9": {
        "Session_code": "",
        "ID": "Oeb797"
    },
    "10": {
        "Session_code": "",
        "ID": "Jur972"
    },
    "11": {
        "Session_code": "",
        "ID": "Cax561"
    },
    "12": {
        "Session_code": "",
        "ID": "Yuv303"
    },
    "13": {
        "Session_code": "",
        "ID": "Neg139"
    },
    "14": {
        "Session_code": "",
        "ID": "Eaq105"
    },
    "15": {
        "Session_code": "",
        "ID": "Suq905"
    },
    "16": {
        "Session_code": "",
        "ID": "Pur805"
    },
    "17": {
        "Session_code": "",
        "ID": "Kag580"
    },
    "18": {
        "Session_code": "",
        "ID": "Uej749"
    },
    "19": {
        "Session_code": "",
        "ID": "Tiw641"
    },
    "20": {
        "Session_code": "",
        "ID": "Eok520"
    },
    "21": {
        "Session_code": "",
        "ID": "Iax258"
    },
    "22": {
        "Session_code": "",
        "ID": "Luv690"
    },
    "23": {
        "Session_code": "",
        "ID": "Yuk827"
    },
    "24": {
        "Session_code": "",
        "ID": "Kig156"
    },
    "25": {
        "Session_code": "",
        "ID": "Vox976"
    },
    "26": {
        "Session_code": "",
        "ID": "Keg184"
    },
    "27": {
        "Session_code": "",
        "ID": "Xic891"
    },
    "28": {
        "Session_code": "",
        "ID": "Zur178"
    },
    "29": {
        "Session_code": "",
        "ID": "Ciy661"
    },
    "30": {
        "Session_code": "",
        "ID": "Fuw975"
    },
    "31": {
        "Session_code": "",
        "ID": "Saq887"
    },
    "32": {
        "Session_code": "",
        "ID": "Iih227"
    },
    "33": {
        "Session_code": "",
        "ID": "Cej375"
    },
    "34": {
        "Session_code": "",
        "ID": "Eor141"
    },
    "35": {
        "Session_code": "",
        "ID": "Zef167"
    },
    "36": {
        "Session_code": "",
        "ID": "Pep711"
    },
    "37": {
        "Session_code": "",
        "ID": "Nez222"
    },
    "38": {
        "Session_code": "",
        "ID": "Qiq774"
    },
    "39": {
        "Session_code": "",
        "ID": "Juc956"
    },
    "40": {
        "Session_code": "",
        "ID": "Eel850"
    },
    "41": {
        "Session_code": "",
        "ID": "Rup388"
    },
    "42": {
        "Session_code": "",
        "ID": "Wem760"
    },
    "43": {
        "Session_code": "",
        "ID": "Dav163"
    },
    "44": {
        "Session_code": "",
        "ID": "Fad920"
    },
    "45": {
        "Session_code": "",
        "ID": "Uab449"
    },
    "46": {
        "Session_code": "",
        "ID": "Eij655"
    },
    "47": {
        "Session_code": "",
        "ID": "Wol446"
    },
    "48": {
        "Session_code": "",
        "ID": "Hom000"
    },
    "49": {
        "Session_code": "",
        "ID": "Voy701"
    },
    "50": {
        "Session_code": "",
        "ID": "Vik154"
    },
    "51": {
        "Session_code": "",
        "ID": "Kaj262"
    },
    "52": {
        "Session_code": "",
        "ID": "Iol785"
    },
    "53": {
        "Session_code": "",
        "ID": "Xeb318"
    },
    "54": {
        "Session_code": "",
        "ID": "Suz054"
    },
    "55": {
        "Session_code": "",
        "ID": "Ief400"
    },
    "56": {
        "Session_code": "",
        "ID": "Has020"
    },
    "57": {
        "Session_code": "",
        "ID": "Bir449"
    },
    "58": {
        "Session_code": "",
        "ID": "Mav412"
    },
    "59": {
        "Session_code": "",
        "ID": "Hah592"
    },
    "60": {
        "Session_code": "",
        "ID": "Uuh542"
    },
    "61": {
        "Session_code": "",
        "ID": "Zuk072"
    },
    "62": {
        "Session_code": "",
        "ID": "Weg829"
    },
    "63": {
        "Session_code": "",
        "ID": "Feg546"
    },
    "64": {
        "Session_code": "",
        "ID": "Zis377"
    },
    "65": {
        "Session_code": "",
        "ID": "Zek581"
    },
    "66": {
        "Session_code": "",
        "ID": "Gug983"
    },
    "67": {
        "Session_code": "",
        "ID": "Wul247"
    },
    "68": {
        "Session_code": "",
        "ID": "His203"
    },
    "69": {
        "Session_code": "",
        "ID": "Eax805"
    },
    "70": {
        "Session_code": "",
        "ID": "Qik988"
    },
    "71": {
        "Session_code": "",
        "ID": "Lit125"
    },
    "72": {
        "Session_code": "",
        "ID": "Seh512"
    },
    "73": {
        "Session_code": "",
        "ID": "Num718"
    },
    "74": {
        "Session_code": "",
        "ID": "Zaf675"
    },
    "75": {
        "Session_code": "",
        "ID": "Xuq022"
    },
    "76": {
        "Session_code": "",
        "ID": "Jas181"
    },
    "77": {
        "Session_code": "",
        "ID": "Cod321"
    },
    "78": {
        "Session_code": "",
        "ID": "Iih329"
    },
    "79": {
        "Session_code": "",
        "ID": "Foj331"
    },
    "80": {
        "Session_code": "",
        "ID": "Uor634"
    },
    "81": {
        "Session_code": "",
        "ID": "Uix718"
    },
    "82": {
        "Session_code": "",
        "ID": "Yar903"
    },
    "83": {
        "Session_code": "",
        "ID": "Tet031"
    },
    "84": {
        "Session_code": "",
        "ID": "Waw925"
    },
    "85": {
        "Session_code": "",
        "ID": "Wiw137"
    },
    "86": {
        "Session_code": "",
        "ID": "Aaw881"
    },
    "87": {
        "Session_code": "",
        "ID": "Jaj390"
    },
    "88": {
        "Session_code": "",
        "ID": "Yon789"
    },
    "89": {
        "Session_code": "",
        "ID": "Fum888"
    },
    "90": {
        "Session_code": "",
        "ID": "Cin374"
    },
    "91": {
        "Session_code": "",
        "ID": "Rik200"
    },
    "92": {
        "Session_code": "",
        "ID": "Cab943"
    },
    "93": {
        "Session_code": "",
        "ID": "Xiy525"
    },
    "94": {
        "Session_code": "",
        "ID": "Tuw770"
    },
    "95": {
        "Session_code": "",
        "ID": "Uam515"
    },
    "96": {
        "Session_code": "",
        "ID": "Yax149"
    },
    "97": {
        "Session_code": "",
        "ID": "Cut458"
    },
    "98": {
        "Session_code": "",
        "ID": "Pak586"
    },
    "99": {
        "Session_code": "",
        "ID": "Nud433"
    },
    "100": {
        "Session_code": "",
        "ID": "Nas936"
    },
    "101": {
        "Session_code": "",
        "ID": "Vup906"
    },
    "102": {
        "Session_code": "",
        "ID": "Liv655"
    },
    "103": {
        "Session_code": "",
        "ID": "Nip163"
    },
    "104": {
        "Session_code": "",
        "ID": "Eiy144"
    },
    "105": {
        "Session_code": "",
        "ID": "Dij587"
    },
    "106": {
        "Session_code": "",
        "ID": "Gag319"
    },
    "107": {
        "Session_code": "",
        "ID": "Yuj087"
    },
    "108": {
        "Session_code": "",
        "ID": "Hot443"
    },
    "109": {
        "Session_code": "",
        "ID": "Uap241"
    },
    "110": {
        "Session_code": "",
        "ID": "Rew886"
    },
    "111": {
        "Session_code": "",
        "ID": "Gas984"
    },
    "112": {
        "Session_code": "",
        "ID": "Gak111"
    },
    "113": {
        "Session_code": "",
        "ID": "Uow082"
    },
    "114": {
        "Session_code": "",
        "ID": "Fib201"
    },
    "115": {
        "Session_code": "",
        "ID": "Dal859"
    },
    "116": {
        "Session_code": "",
        "ID": "Wab840"
    },
    "117": {
        "Session_code": "",
        "ID": "Uap601"
    },
    "118": {
        "Session_code": "",
        "ID": "Rif597"
    },
    "119": {
        "Session_code": "",
        "ID": "Cix321"
    },
    "120": {
        "Session_code": "",
        "ID": "Son147"
    },
    "121": {
        "Session_code": "",
        "ID": "Xam534"
    },
    "122": {
        "Session_code": "",
        "ID": "Jem947"
    },
    "123": {
        "Session_code": "",
        "ID": "Lot189"
    },
    "124": {
        "Session_code": "",
        "ID": "Qam603"
    },
    "125": {
        "Session_code": "",
        "ID": "Aij523"
    },
    "126": {
        "Session_code": "",
        "ID": "Dok404"
    },
    "127": {
        "Session_code": "",
        "ID": "Yom276"
    },
    "128": {
        "Session_code": "",
        "ID": "Dow907"
    },
    "129": {
        "Session_code": "",
        "ID": "Zer032"
    },
    "130": {
        "Session_code": "",
        "ID": "Mem257"
    },
    "131": {
        "Session_code": "",
        "ID": "Oix214"
    },
    "132": {
        "Session_code": "",
        "ID": "Qoh240"
    },
    "133": {
        "Session_code": "",
        "ID": "Reb115"
    },
    "134": {
        "Session_code": "",
        "ID": "Yuv856"
    },
    "135": {
        "Session_code": "",
        "ID": "Aar802"
    },
    "136": {
        "Session_code": "",
        "ID": "Num539"
    },
    "137": {
        "Session_code": "",
        "ID": "Cad273"
    },
    "138": {
        "Session_code": "",
        "ID": "Vev982"
    },
    "139": {
        "Session_code": "",
        "ID": "Jef974"
    },
    "140": {
        "Session_code": "",
        "ID": "Lok766"
    },
    "141": {
        "Session_code": "",
        "ID": "Vaz872"
    },
    "142": {
        "Session_code": "",
        "ID": "Fid793"
    },
    "143": {
        "Session_code": "",
        "ID": "Tax827"
    },
    "144": {
        "Session_code": "",
        "ID": "Vav225"
    },
    "145": {
        "Session_code": "",
        "ID": "Kiq681"
    },
    "146": {
        "Session_code": "",
        "ID": "Miy806"
    },
    "147": {
        "Session_code": "",
        "ID": "Fun274"
    },
    "148": {
        "Session_code": "",
        "ID": "Nej863"
    },
    "149": {
        "Session_code": "",
        "ID": "Kum854"
    },
    "150": {
        "Session_code": "",
        "ID": "Yap112"
    },
    "151": {
        "Session_code": "",
        "ID": "Sar297"
    },
    "152": {
        "Session_code": "",
        "ID": "Siq310"
    },
    "153": {
        "Session_code": "",
        "ID": "Kir972"
    },
    "154": {
        "Session_code": "",
        "ID": "Qid144"
    },
    "155": {
        "Session_code": "",
        "ID": "Xoj895"
    },
    "156": {
        "Session_code": "",
        "ID": "Uuw843"
    },
    "157": {
        "Session_code": "",
        "ID": "Bay836"
    },
    "158": {
        "Session_code": "",
        "ID": "Mok131"
    },
    "159": {
        "Session_code": "",
        "ID": "Eec470"
    },
    "160": {
        "Session_code": "",
        "ID": "Min240"
    },
    "161": {
        "Session_code": "",
        "ID": "Yof024"
    },
    "162": {
        "Session_code": "",
        "ID": "Lis162"
    },
    "163": {
        "Session_code": "",
        "ID": "Lic544"
    },
    "164": {
        "Session_code": "",
        "ID": "Mec912"
    },
    "165": {
        "Session_code": "",
        "ID": "Fex091"
    },
    "166": {
        "Session_code": "",
        "ID": "Bub831"
    },
    "167": {
        "Session_code": "",
        "ID": "Suf045"
    },
    "168": {
        "Session_code": "",
        "ID": "Pax770"
    },
    "169": {
        "Session_code": "",
        "ID": "Zep825"
    },
    "170": {
        "Session_code": "",
        "ID": "Duq767"
    },
    "171": {
        "Session_code": "",
        "ID": "Euv412"
    },
    "172": {
        "Session_code": "",
        "ID": "Hog984"
    },
    "173": {
        "Session_code": "",
        "ID": "Nek973"
    },
    "174": {
        "Session_code": "",
        "ID": "Mob244"
    },
    "175": {
        "Session_code": "",
        "ID": "Qim108"
    },
    "176": {
        "Session_code": "",
        "ID": "Gim228"
    },
    "177": {
        "Session_code": "",
        "ID": "Cub597"
    },
    "178": {
        "Session_code": "",
        "ID": "Biv837"
    },
    "179": {
        "Session_code": "",
        "ID": "Kiq453"
    },
    "180": {
        "Session_code": "",
        "ID": "Xoy750"
    },
    "181": {
        "Session_code": "",
        "ID": "Pec648"
    },
    "182": {
        "Session_code": "",
        "ID": "Poq152"
    },
    "183": {
        "Session_code": "",
        "ID": "Gaw791"
    },
    "184": {
        "Session_code": "",
        "ID": "Kig951"
    },
    "185": {
        "Session_code": "",
        "ID": "Der255"
    },
    "186": {
        "Session_code": "",
        "ID": "Yel201"
    },
    "187": {
        "Session_code": "",
        "ID": "Qoz194"
    },
    "188": {
        "Session_code": "",
        "ID": "Oom927"
    },
    "189": {
        "Session_code": "",
        "ID": "Wir647"
    },
    "190": {
        "Session_code": "",
        "ID": "Iiv111"
    },
    "191": {
        "Session_code": "",
        "ID": "Qen480"
    },
    "192": {
        "Session_code": "",
        "ID": "Jos939"
    },
    "193": {
        "Session_code": "",
        "ID": "Zab914"
    },
    "194": {
        "Session_code": "",
        "ID": "Zep608"
    },
    "195": {
        "Session_code": "",
        "ID": "Yam781"
    },
    "196": {
        "Session_code": "",
        "ID": "Raj642"
    },
    "197": {
        "Session_code": "",
        "ID": "Rod570"
    },
    "198": {
        "Session_code": "",
        "ID": "Wor245"
    },
    "199": {
        "Session_code": "",
        "ID": "Hos595"
    },
    "200": {
        "Session_code": "",
        "ID": "Ciw665"
    }
}